Metadata-Version: 2.1
Name: PythonTurtle
Version: 0.3.1
Summary: An educational environment for learning Python, suitable for beginners
Home-page: http://pythonturtle.org
Author: Ram Rachum
Author-email: ram@rachum.com
License: MIT
Project-URL: Source, https://github.com/cool-RR/PythonTurtle
Keywords: turtle,learning,children,beginners,logo
Platform: UNKNOWN
Classifier: Development Status :: 5 - Production/Stable
Classifier: Environment :: MacOS X
Classifier: Environment :: Win32 (MS Windows)
Classifier: Environment :: X11 Applications :: GTK
Classifier: Intended Audience :: Education
Classifier: License :: OSI Approved :: MIT License
Classifier: Operating System :: MacOS
Classifier: Operating System :: Microsoft :: Windows
Classifier: Operating System :: POSIX :: Linux
Classifier: Programming Language :: Python :: 3
Classifier: Programming Language :: Python :: 3.6
Classifier: Programming Language :: Python :: 3.7
Classifier: Topic :: Education
Requires-Python: >=3
